webshocket/__init__.py
webshocket/connection.py
webshocket/connection.pyi
webshocket/enum.py
webshocket/exceptions.py
webshocket/handler.py
webshocket/packets.py
webshocket/predicate.py
webshocket/py.typed
webshocket/rpc.py
webshocket/typing.py
webshocket/utils.py
webshocket/websocket.py
webshocket/websocket.pyi
webshocket-0.4.0.dist-info/licenses/LICENSE
webshocket-0.4.0.dist-info/METADATA
webshocket-0.4.0.dist-info/WHEEL
webshocket-0.4.0.dist-info/top_level.txt
webshocket-0.4.0.dist-info/RECORD
